py3_service_check/__init__.py
py3_service_check/processor.py
scione5_auto_check/__init__.py
scione5_auto_check/file_uploader.py
scione5_auto_check/file_uploader_v2.py
scione5_auto_check/main_process.py
scione5_auto_check/mysql_client.py
scione5_auto_check/scione5_encrypt.py
scione5_auto_check/test_handler.py
py3_service_check-0.3.1.dist-info/LICENSE
py3_service_check-0.3.1.dist-info/METADATA
py3_service_check-0.3.1.dist-info/WHEEL
py3_service_check-0.3.1.dist-info/top_level.txt
py3_service_check-0.3.1.dist-info/RECORD
